{
  "type": "app-service",
  "name": "my-service",
  "description": "",
  "singleton": true,
  "variables": [
    {
      "name": "graphql",
      "type": "graphql-api",
      "id": "graphql-api"
    },
    {
      "name": "swaggerApi",
      "type": "open-api",
      "id": "open-api"
    },
    {
      "name": "restApiRenamed",
      "type": "open-api",
      "id": "open-api"
    },
    {
      "name": "swagger",
      "description": "",
      "type": "method",
      "body": "$ctrl.swaggerApi.findPetsByStatus({\n    status: \"available\"\n}).then(result => {\n    $ctrl.pets = result.data\n})",
      "invokeOnLoad": true,
      "isAsync": false,
      "returnType": {
        "name": "any"
      },
      "parameters": [],
      "watch": []
    },
    {
      "name": "graphFnc",
      "description": "",
      "type": "method",
      "body": "$ctrl.graphql.query.weather({\ncity: \"New York\" },\n    {\n        id: true,\n        cityName: true,\n        currentWeather: {\n            description: true,\n            humidity: true,\n            pressure: true,\n            status: true,\n            temp: true,\n            tempHigh: true,\n            tempLow: true,\n            windSpeed: true,\n        },\n    })\n    .then((result) => {\n        $ctrl.results = JSON.stringify(result, null, 2);\n    })",
      "invokeOnLoad": true,
      "isAsync": false,
      "returnType": {
        "name": "any"
      },
      "parameters": [],
      "watch": []
    },
    {
      "name": "rest",
      "description": "",
      "type": "method",
      "body": "$ctrl.restApi.getObjects().then(result => {\n    $ctrl.obj = result.data\n})",
      "invokeOnLoad": true,
      "isAsync": false,
      "returnType": {
        "name": "any"
      },
      "parameters": [],
      "watch": []
    }
  ],
  "visible": [],
  "parentDirectoryId": null
}